{
  "ticker": "MU",
  "timeframe": "weekly",
  "source_daily_lookback": 250,
  "weekly_candle_count": 52,
  "zone_count": 5,
  "zones": [
    {
      "type": "resistance",
      "low": 124.16,
      "high": 124.24,
      "touches": 2
    },
    {
      "type": "support",
      "low": 192.4,
      "high": 192.59,
      "touches": 2
    },
    {
      "type": "support",
      "low": 363.9,
      "high": 364.1,
      "touches": 2
    },
    {
      "type": "support",
      "low": 91.95,
      "high": 92.22,
      "touches": 2
    },
    {
      "type": "resistance",
      "low": 470.97,
      "high": 471.34,
      "touches": 2
    }
  ]
}